pase/__init__.py
pase/pase.py
pase-3.0.6.dist-info/METADATA
pase-3.0.6.dist-info/WHEEL
pase-3.0.6.dist-info/top_level.txt
pase-3.0.6.dist-info/RECORD
