Metadata-Version: 2.1
Name: pase
Version: 3.0.6
Summary: Python Audio Spectrogram Explorer: a GUI to visualize audio files as spectrograms, log annotations and extract time-frequency shapes
Home-page: https://github.com/sebastianmenze/Python-Audio-Spectrogram-Explorer
Author: Sebastian Menze
Author-email: sebastian.menze@gmail.com
License: MIT
Classifier: License :: OSI Approved :: MIT License
Classifier: Programming Language :: Python :: 3.9
Requires-Dist: soundfile
Requires-Dist: simpleaudio
Requires-Dist: scikit-image
Requires-Dist: moviepy
